Workbook

Sheet PG_1_Analysis
B2: P&G | Revenue growth and operating profit
B4: FY2026 sales grew; operating profit declined. Amounts in USD millions.
B6: Metric | C6: FY2024 | D6: FY2025 | E6: FY2026 | F6: FY26 vs FY25
B7: Net sales | C7: ='Reported Earnings'!C7 -> 84039 | D7: ='Reported Earnings'!D7 -> 84284 | E7: ='Reported Earnings'!E7 -> 87032 | F7: =E7-D7 -> 2748
B8: Cost of products sold | C8: ='Reported Earnings'!C8 -> 40848 | D8: ='Reported Earnings'!D8 -> 41164 | E8: ='Reported Earnings'!E8 -> 43362 | F8: =E8-D8 -> 2198
B9: Gross profit | C9: =C7-C8 -> 43191 | D9: =D7-D8 -> 43120 | E9: =E7-E8 -> 43670 | F9: =E9-D9 -> 550
B10: SG&A | C10: ='Reported Earnings'!C9 -> 23305 | D10: ='Reported Earnings'!D9 -> 22669 | E10: ='Reported Earnings'!E9 -> 23922 | F10: =E10-D10 -> 1253
B11: Intangible impairment | C11: ='Reported Earnings'!C10 -> 1341 | D11: ='Reported Earnings'!D10 -> 0 | E11: ='Reported Earnings'!E10 -> 0 | F11: =E11-D11 -> 0
B12: Operating income | C12: ='Reported Earnings'!C11 -> 18545 | D12: ='Reported Earnings'!D11 -> 20451 | E12: ='Reported Earnings'!E11 -> 19748 | F12: =E12-D12 -> -703
B14: Gross margin | C14: =C9/C7 -> 0.51393996 | D14: =D9/D7 -> 0.51160363 | E14: =E9/E7 -> 0.50176946 | F14: =(E14-D14)*10000 -> -98.341617
B15: Operating margin | C15: =C12/C7 -> 0.22067135 | D15: =D12/D7 -> 0.24264392 | E15: =E12/E7 -> 0.22690505 | F15: =(E15-D15)*10000 -> -157.38872
B17: FY2026 growth vs FY2025 | C17: Revenue | D17: =E7/D7-1 -> 0.032604053 | E17: Operating profit | F17: =E12/D12-1 -> -0.034374847
B19: Operating profit bridge | C19: Effect (USD m)
B20: Revenue increase | C20: =F7 -> 2748
B21: Higher cost of products sold | C21: =-F8 -> -2198
B22: Higher SG&A | C22: =-F10 -> -1253
B23: Change in impairment | C23: =-F11 -> 0
B24: Net operating profit change | C24: =SUM(C20:C23) -> -703
B26: Bridge less reported operating profit change | C26: =C24-F12 -> 0
B28: Reported: source financial amounts. Derived: gross profit, margins and changes.
B29: FY2024 includes $1,341m impairment; the FY2025 recovery is not fully recurring.
B30: Gross profit uses net sales less cost of products sold; no adjusted series created.

Sheet Reported Earnings
B2: P&G | Reported income statement
B4: Fiscal years ended 30 June; USD millions, except EPS
B6: Reported metric | C6: FY2024 | D6: FY2025 | E6: FY2026 | F6: Classification
B7: Net sales | C7: 84039 | D7: 84284 | E7: 87032 | F7: Reported
B8: Cost of products sold | C8: 40848 | D8: 41164 | E8: 43362 | F8: Reported
B9: Selling, general and administrative expense | C9: 23305 | D9: 22669 | E9: 23922 | F9: Reported
B10: Intangible asset impairment | C10: 1341 | D10: 0 | E10: 0 | F10: Reported
B11: Operating income | C11: 18545 | D11: 20451 | E11: 19748 | F11: Reported
B12: Interest expense | C12: -925 | D12: -907 | E12: -877 | F12: Reported
B13: Interest income | C13: 473 | D13: 469 | E13: 430 | F13: Reported
B14: Other non-operating income, net | C14: 668 | D14: 154 | E14: 1076 | F14: Reported
B15: Earnings before income taxes | C15: 18761 | D15: 20167 | E15: 20377 | F15: Reported
B16: Income taxes | C16: 3787 | D16: 4102 | E16: 4233 | F16: Reported
B17: Net earnings | C17: 14974 | D17: 16065 | E17: 16144 | F17: Reported
B18: Net earnings attributable to noncontrolling interests | C18: 95 | D18: 91 | E18: 98 | F18: Reported
... B21: Diluted EPS | C21: 6.02 | D21: 6.51 | E21: 6.62 | F21: Reported
B23: Source: P&G 2026 Annual Report, printed p.37 (PDF p.49).
B24: Company financial spreadsheet: income statement, rows 5–21.
B25: Source dashes on impairment are recorded as zero; no adjustments made.
B26: Red marks highlight matching evidence, not a positive or negative result.
B28: https://s204.q4cdn.com/332108499/files/doc_financials/2026/ar/2026_annual_report.pdf
